[
null,
{"id":1,"actions":[],"battlerHue":0,"battlerName":"","dropItems":[{"dataId":1,"denominator":1,"kind":0},{"dataId":1,"denominator":1,"kind":0},{"dataId":1,"denominator":1,"kind":0}],"exp":0,"traits":[{"code":22,"dataId":1,"value":1}],"gold":0,"name":"Useless Destructable","note":"<AIType:none>\n<noPopup>\n<noHpBar>\n<respawn:60>\n\nNote: You can actually add invincibility to\nthese boxes by making them immunte to the\ncorresponding elements.","params":[1,0,1,1,1,1,1,1]},
{"id":2,"actions":[{"conditionParam1":0,"conditionParam2":0,"conditionType":0,"rating":5,"skillId":31}],"battlerHue":0,"battlerName":"Ghost","dropItems":[{"kind":1,"dataId":4,"denominator":5},{"kind":1,"dataId":5,"denominator":8},{"kind":1,"dataId":6,"denominator":3}],"exp":15,"traits":[{"code":31,"dataId":1,"value":0}],"gold":10,"name":"TEST EN","note":"<respawn:240>\n<level: 17>\n<gpMod: 4>\n<i:2:95>\n<onDeath>\n$gameVariables.setValue(10, $gameVariables.value(10) + 1);\n</onDeath>","params":[100,0,20,20,20,20,20,20]},
{"id":3,"actions":[],"battlerHue":0,"battlerName":"","dropItems":[{"dataId":1,"denominator":1,"kind":0},{"dataId":1,"denominator":1,"kind":0},{"dataId":1,"denominator":1,"kind":0}],"exp":0,"traits":[],"gold":0,"name":"TEST BOX","note":"<AIType:none>\n<noPopup>\n<noHpBar>\n<respawn:120>\n<rev:swi:1:true>\n<onDeath>\n$gameVariables.setValue(1, $gameVariables.value(1) + 1);\n</onDeath>","params":[1,0,1,1,1,1,1,1]},
{"id":4,"actions":[{"conditionParam1":0,"conditionParam2":0,"conditionType":0,"rating":5,"skillId":2}],"battlerHue":0,"battlerName":"","dropItems":[{"kind":0,"dataId":0,"denominator":1},{"dataId":1,"denominator":1,"kind":0},{"dataId":1,"denominator":1,"kind":0}],"exp":0,"traits":[{"code":22,"dataId":1,"value":1}],"gold":0,"name":"Campfire","note":"Note that we set the evasion rate to 100%\nThis is because in the plugin parameters\nwe're using evasion rate for the move\nresist state. We don't want this enemy\nto be able to be moved\n\n<AIType:none>\n<noPopup>\n<noHpBar>\n\nWe're going to give this enemy some custom\nAI with eventing. So first we'll add an\nondeath tag to turn on a self switch\nthen the dontErase tag so the event can\nkeep running even if it's dead. The rest\nof the AI is inside the events page.\n\n<onDeath>\nthis.setSelfSwitch('A', true);\n</onDeath>\n<dontErase>","params":[1,100,10,10,10,10,10,10]},
{"id":5,"actions":[{"conditionParam1":0,"conditionParam2":0,"conditionType":0,"rating":5,"skillId":34}],"battlerHue":250,"battlerName":"Ghost","dropItems":[{"kind":1,"dataId":4,"denominator":40},{"kind":1,"dataId":5,"denominator":20},{"kind":1,"dataId":6,"denominator":5}],"exp":6,"traits":[{"code":31,"dataId":1,"value":0}],"gold":3,"name":"Ghosty","note":"<AIType:simple>\n<respawn:60>\n<level: 3>\n<gpMod: 2>","params":[150,0,10,10,10,10,10,10]},
{"id":6,"actions":[],"battlerHue":293,"battlerName":"Slime","dropItems":[{"dataId":1,"denominator":1,"kind":0},{"dataId":1,"denominator":1,"kind":0},{"dataId":1,"denominator":1,"kind":0}],"exp":40,"traits":[{"code":22,"dataId":1,"value":0.5}],"gold":20,"name":"Boss Slime","note":"<AIType:simple>\n<level: 5>\n<gpMod: 5>","params":[800,0,1,20,1,20,1,1]},
{"id":7,"actions":[{"conditionParam1":0,"conditionParam2":0,"conditionType":0,"rating":5,"skillId":1}],"battlerHue":0,"battlerName":"","dropItems":[{"dataId":1,"denominator":1,"kind":0},{"dataId":1,"denominator":1,"kind":0},{"dataId":1,"denominator":1,"kind":0}],"exp":0,"traits":[{"code":22,"dataId":0,"value":0.95},{"code":22,"dataId":1,"value":0.05},{"code":31,"dataId":1,"value":0}],"gold":0,"name":"","note":"","params":[100,0,10,10,10,10,10,10]}
]